Metadata-Version: 2.1
Name: tsatsu-email-sender
Version: 0.0.2
Summary: A package to send emails
Home-page: 
Author: Akorlie Edward Tsatsu
Author-email: edwardakorlie73@gmail.com
License: MIT
Keywords: email
Classifier: Development Status :: 5 - Production/Stable
Classifier: Intended Audience :: Education
Classifier: Operating System :: Microsoft :: Windows :: Windows 10
Classifier: License :: OSI Approved :: MIT License
Classifier: Programming Language :: Python :: 3
